Metadata-Version: 1.1
Name: pyladies-digest
Version: 0.31
Summary: Command line tool to create a MailChimp template for PyLadies chapters
Home-page: https://github.com/lorenanicole/chicago-pyladies-digest
Author: Lorena Mesa
Author-email: me@lorenamesa.com
License: MIT
Keywords: pyladies email digest mailchimp
Platform: UNKNOWN
Classifier: License :: OSI Approved :: MIT License
Classifier: Programming Language :: Python :: 2.7
